greek_parcel/__init__.py
greek_parcel/__main__.py
greek_parcel/cli/__init__.py
greek_parcel/cli/commands.py
greek_parcel/cli/interactions.py
greek_parcel/core/__init__.py
greek_parcel/core/constants.py
greek_parcel/core/exceptions.py
greek_parcel/core/identification.py
greek_parcel/core/logging_config.py
greek_parcel/core/models.py
greek_parcel/core/storage.py
greek_parcel/trackers/__init__.py
greek_parcel/trackers/acs.py
greek_parcel/trackers/base.py
greek_parcel/trackers/boxnow.py
greek_parcel/trackers/courier_center.py
greek_parcel/trackers/easymail.py
greek_parcel/trackers/elta.py
greek_parcel/trackers/geniki.py
greek_parcel/trackers/skroutz.py
greek_parcel/trackers/speedex.py
greek_parcel/utils/__init__.py
greek_parcel/utils/display.py
greek_parcel/utils/notify.py
greek_parcel/utils/user_agents.py
greek_parcel_cli-0.5.0.dist-info/licenses/LICENSE
greek_parcel_cli-0.5.0.dist-info/METADATA
greek_parcel_cli-0.5.0.dist-info/WHEEL
greek_parcel_cli-0.5.0.dist-info/entry_points.txt
greek_parcel_cli-0.5.0.dist-info/top_level.txt
greek_parcel_cli-0.5.0.dist-info/RECORD
