Metadata-Version: 2.4
Name: greek-parcel-cli
Version: 0.5.0
Summary: A CLI tool for tracking parcels from Greek courier services.
Author-email: Ilias Nikolaos Thalassochoritis <iliascodes@gmail.com>
License-Expression: MIT
Project-URL: Homepage, https://github.com/eliac7/Greek-Parcel-CLI
Project-URL: Documentation, https://github.com/eliac7/Greek-Parcel-CLI#readme
Project-URL: Repository, https://github.com/eliac7/Greek-Parcel-CLI
Project-URL: Issues, https://github.com/eliac7/Greek-Parcel-CLI/issues
Keywords: parcel,tracking,courier,greek,cli,package-tracking,shipping
Classifier: Development Status :: 4 - Beta
Classifier: Intended Audience :: End Users/Desktop
Classifier: Operating System :: OS Independent
Classifier: Programming Language :: Python :: 3
Classifier: Programming Language :: Python :: 3.9
Classifier: Programming Language :: Python :: 3.10
Classifier: Programming Language :: Python :: 3.11
Classifier: Programming Language :: Python :: 3.12
Classifier: Topic :: Utilities
Requires-Python: >=3.9
License-File: LICENSE
Requires-Dist: beautifulsoup4
Requires-Dist: lxml
Requires-Dist: plyer
Requires-Dist: requests
Requires-Dist: rich
Requires-Dist: typer
Requires-Dist: ua-generator
Dynamic: license-file
